django_async_backend/__init__.py
django_async_backend/apps.py
django_async_backend/db/__init__.py
django_async_backend/db/backends/base/__init__.py
django_async_backend/db/backends/base/base.py
django_async_backend/db/backends/postgresql/__init__.py
django_async_backend/db/backends/postgresql/async_base.py
django_async_backend/db/backends/postgresql/base.py
django_async_backend/db/backends/utils.py
django_async_backend/db/transaction.py
django_async_backend/db/utils.py
django_async_backend/test.py
django_async_backend/utils/__init__.py
django_async_backend/utils/await_maybe.py
django_async_backend/utils/connection.py
django_async_backend-0.0.2.dist-info/LICENSE
django_async_backend-0.0.2.dist-info/METADATA
django_async_backend-0.0.2.dist-info/WHEEL
django_async_backend-0.0.2.dist-info/RECORD
